ina260/__init__.py
ina260/controller.py
ina260-0.0.2.dist-info/WHEEL
ina260-0.0.2.dist-info/METADATA
ina260-0.0.2.dist-info/RECORD
